lernziel_api.py
lernziel_api-0.0.1.dist-info/LICENSE
lernziel_api-0.0.1.dist-info/METADATA
lernziel_api-0.0.1.dist-info/WHEEL
lernziel_api-0.0.1.dist-info/top_level.txt
lernziel_api-0.0.1.dist-info/RECORD
